reinvent_2025_mcp/__init__.py
reinvent_2025_mcp/main.py
reinvent_2025_mcp/data/__init__.py
reinvent_2025_mcp/data/loader.py
reinvent_2025_mcp/data/sessions.msgpack
reinvent_2025_mcp/services/__init__.py
reinvent_2025_mcp/services/session_service.py
reinvent_2025_mcp/tools/__init__.py
reinvent_2025_mcp/tools/session_tools.py
re_invent_2025_mcp-1.0.4.dist-info/METADATA
re_invent_2025_mcp-1.0.4.dist-info/WHEEL
re_invent_2025_mcp-1.0.4.dist-info/entry_points.txt
re_invent_2025_mcp-1.0.4.dist-info/RECORD
