Metadata-Version: 2.4
Name: re-invent-2025-mcp
Version: 1.0.4
Summary: MCP server for re:Invent 2025 session catalog with 1,843 sessions and 13 search tools
Project-URL: Homepage, https://github.com/manu-mishra/reinvent-mcp-2025
Project-URL: Repository, https://github.com/manu-mishra/reinvent-mcp-2025
Project-URL: Issues, https://github.com/manu-mishra/reinvent-mcp-2025/issues
Project-URL: LinkedIn, https://www.linkedin.com/in/manu-mishra/
Author: Manu Mishra
License: MIT
Keywords: 2025,conference,mcp,model-context-protocol,reinvent,sessions
Classifier: Development Status :: 4 - Beta
Classifier: Intended Audience :: Developers
Classifier: License :: OSI Approved :: MIT License
Classifier: Programming Language :: Python :: 3
Classifier: Programming Language :: Python :: 3.11
Classifier: Programming Language :: Python :: 3.12
Classifier: Topic :: Internet :: WWW/HTTP :: Dynamic Content
Classifier: Topic :: Software Development :: Libraries :: Python Modules
Requires-Python: >=3.11
Requires-Dist: mcp>=1.15.0
Requires-Dist: msgpack>=1.1.0
Provides-Extra: test
Requires-Dist: pytest-asyncio>=0.23.0; extra == 'test'
Requires-Dist: pytest>=8.0.0; extra == 'test'
